strefi/__init__.py
strefi/__main__.py
strefi/command.py
strefi/kafka_utils.py
strefi/parser.py
strefi/supervisor.py
strefi-0.2.0.dist-info/METADATA
strefi-0.2.0.dist-info/WHEEL
strefi-0.2.0.dist-info/entry_points.txt
strefi-0.2.0.dist-info/top_level.txt
strefi-0.2.0.dist-info/RECORD
