Metadata-Version: 2.1
Name: strefi
Version: 0.2.0
Summary: Stream each new rows of a file and write in kafka
Home-page: https://github.com/VictorMeyer77/strefi
Author: Victor Meyer
Project-URL: Bug Tracker, https://github.com/VictorMeyer77/strefi/issues
Project-URL: Changelog, https://github.com/VictorMeyer77/strefi/blob/main/CHANGELOG.md
Project-URL: Documentation, https://strefi.readthedocs.io
Project-URL: Source, https://github.com/VictorMeyer77/strefi
Classifier: Development Status :: 4 - Beta
Classifier: Environment :: Console
Classifier: Intended Audience :: Developers
Classifier: License :: OSI Approved :: GNU General Public License v3 (GPLv3)
Classifier: Operating System :: MacOS :: MacOS X
Classifier: Operating System :: POSIX :: Linux
Classifier: Operating System :: Microsoft :: Windows
Classifier: Programming Language :: Python
Requires-Dist: kafka-python >=2.0.2
Provides-Extra: test
Requires-Dist: pytest ; extra == 'test'
Requires-Dist: pytest-timeout ; extra == 'test'
Requires-Dist: coverage ; extra == 'test'
Requires-Dist: flake8 ; extra == 'test'
Requires-Dist: black ; extra == 'test'
Requires-Dist: isort ; extra == 'test'
Requires-Dist: pytest-cov ; extra == 'test'
Requires-Dist: mypy ; extra == 'test'
Requires-Dist: mkdocs ; extra == 'test'
Requires-Dist: mkdocstrings ; extra == 'test'
Requires-Dist: mkdocstrings-python ; extra == 'test'
Requires-Dist: kafka-python >=2.0.2 ; extra == 'test'
